pylsp_pylama/__init__.py
pylsp_pylama/plugin.py
pylsp_pylama/version.py
tools/bootstrap_venvstarter.py
tools/devtools.py
python_lsp_pylama-0.1.dist-info/METADATA
python_lsp_pylama-0.1.dist-info/WHEEL
python_lsp_pylama-0.1.dist-info/entry_points.txt
python_lsp_pylama-0.1.dist-info/licenses/LICENSE
python_lsp_pylama-0.1.dist-info/RECORD
