Metadata-Version: 2.1
Name: python-lsp-pylama
Version: 0.1
Summary: pylama linting plugin for pylsp
Project-URL: Homepage, https://github.com/delfick/python-lsp-pylama
Author-email: Stephen Moore <stephen@delfick.com>
License: MIT
License-File: LICENSE
Requires-Python: >=3.7
Requires-Dist: lsprotocol>=2022.0.0a1
Requires-Dist: pylama>=8.0.0
Requires-Dist: python-lsp-server
Requires-Dist: tomli>=1.1.0; python_version < '3.11'
Provides-Extra: tests
Requires-Dist: noseofyeti[black]==2.4.1; extra == 'tests'
Requires-Dist: pytest==7.3.0; extra == 'tests'
